Metadata-Version: 1.1
Name: bylogger
Version: 1.0.2
Summary: Logging Library with fluent-logger wrapper
Home-page: https://github.com/ByPrice/bylogger
Author: Yogesh
Author-email: yogesh@byprice.com
License: MIT
Download-URL: https://github.com/ByPrice/bylogger/
Keywords: ByPrice,logger with fluent,fluent-logger,python-logging
Platform: cross-platfom
Platform: platform-independent
Classifier: Development Status :: 3 - Alpha
Classifier: Intended Audience :: Developers
Classifier: Topic :: Software Development :: Build Tools
Classifier: Programming Language :: Python :: 3.6
